<?xml version="1.0" encoding="utf-8" ?><dwsync><file name="index.php" server="ftp.ruediheimlicher.ch" local="3411224360" remote="16296122628" /><file name="benutzerauswahl.php" server="ftp.ruediheimlicher.ch" local="3410882636" remote="16295780868" /><file name="lernmedien.css" server="ftp.ruediheimlicher.ch" local="3411135258" remote="16296033528" /><file name="liste.php" server="ftp.ruediheimlicher.ch" local="3411046449" remote="16295944728" /><file name="detailliste.php" server="ftp.ruediheimlicher.ch" local="3411135644" remote="16296033888" /><file name="admin.php" server="ftp.ruediheimlicher.ch" local="3411225437" remote="16296123708" /><file name="adminconfirm.php" server="ftp.ruediheimlicher.ch" local="3411225338" remote="16296123588" /><file name="detailanzeige.php" server="ftp.ruediheimlicher.ch" local="3411046552" remote="16295944788" /></dwsync>